Metadata-Version: 1.0
Name: actorname
Version: 0.0.1
Summary: Generate human-readable, random object names
Home-page: https://launchpad.net/python-actorname
Author: Mark Christopher West
Author-email: markchristopherwest@gmail.com
License: Apache2
Keywords: random name uuid
Platform: any
